apiclarity/__init__.py
apiclarity/client.py
apiclarity/openapispec.py
apiclarity/schemas.py
apiclarity-0.2.0.dist-info/entry_points.txt
apiclarity-0.2.0.dist-info/LICENSE
apiclarity-0.2.0.dist-info/WHEEL
apiclarity-0.2.0.dist-info/METADATA
apiclarity-0.2.0.dist-info/RECORD
