Metadata-Version: 2.1
Name: apiclarity
Version: 0.2.0
Summary: Client python package for interaction with APIClarity.
Home-page: https://github.com/openclarity/python-apiclarity-client
License: Apache-2.0
Author: Jeff Napper
Author-email: jenapper@cisco.com
Requires-Python: >=3.7,<4.0
Classifier: License :: OSI Approved :: Apache Software License
Classifier: Programming Language :: Python :: 3
Classifier: Programming Language :: Python :: 3.7
Classifier: Programming Language :: Python :: 3.8
Classifier: Programming Language :: Python :: 3.9
Classifier: Programming Language :: Python :: 3.10
Classifier: Programming Language :: Python :: 3.11
Requires-Dist: pydantic[dotenv] (>=1.10.4,<2.0.0)
Requires-Dist: requests (>=2.28.1,<3.0.0)
Project-URL: Repository, https://github.com/openclarity/python-apiclarity-client
